Weather_pj01/__init__.py
Weather_pj01-0.0.1.dist-info/LICENSE.txt
Weather_pj01-0.0.1.dist-info/METADATA
Weather_pj01-0.0.1.dist-info/WHEEL
Weather_pj01-0.0.1.dist-info/top_level.txt
Weather_pj01-0.0.1.dist-info/RECORD
