Metadata-Version: 2.1
Name: Weather-pj01
Version: 0.0.1
Summary: Weather Forecast
Home-page: https://github.com/pj-codes
Author: Pulkit Jain
Author-email: jainpulkit206@gmail.com
License: UNKNOWN
Platform: UNKNOWN
Classifier: Programming Language :: Python :: 3
Classifier: License :: OSI Approved :: MIT License
Classifier: Operating System :: OS Independent
